pyBTK/__init__.py
pyBTK/_btk.pyd
pyBTK/btk.py
pyBTK/__pycache__/__init__.cpython-37.pyc
pyBTK/__pycache__/btk.cpython-37.pyc
pyBTK-0.1.1.dist-info/METADATA
pyBTK-0.1.1.dist-info/WHEEL
pyBTK-0.1.1.dist-info/top_level.txt
pyBTK-0.1.1.dist-info/RECORD
