Metadata-Version: 2.1
Name: pyBTK
Version: 0.1.1
Summary: python3 wrapping of the Biomechanical toolkit
Home-page: UNKNOWN
Author: Fabien Leboeuf
Author-email: fabien.leboeuf@gmail.com
License: BSD License
Keywords: c3d,mocap
Platform: UNKNOWN
Classifier: Development Status :: 4 - Beta
Classifier: Programming Language :: Python
Classifier: Programming Language :: Python :: 3.7
Classifier: Operating System :: Microsoft :: Windows
Classifier: Natural Language :: English
Requires-Python: >=3.7
